custom_metrics/__init__.py
custom_metrics/airflow/__init__.py
custom_metrics/airflow/monitoring_operators.py
custom_metrics/helpers/__init__.py
custom_metrics/helpers/stackdriver_metrics.py
airflow_extension_metrics-0.4.79.dist-info/LICENSE
airflow_extension_metrics-0.4.79.dist-info/METADATA
airflow_extension_metrics-0.4.79.dist-info/WHEEL
airflow_extension_metrics-0.4.79.dist-info/top_level.txt
airflow_extension_metrics-0.4.79.dist-info/RECORD
