Metadata-Version: 2.1
Name: airflow-extension-metrics
Version: 0.4.79
Summary: Package to expand Airflow for custom metrics.
Home-page: https://github.com/nytm/airflow_extensions/custom_metrics
Author: Sarah Duncan
Author-email: sarah.duncan@nytimes.com
License: Apache License 2.0
Platform: UNKNOWN
Requires-Dist: google-cloud-monitoring (==0.31.1)
